speedfile/__init__.py
speedfile-0.0.1.dist-info/LICENSE
speedfile-0.0.1.dist-info/METADATA
speedfile-0.0.1.dist-info/WHEEL
speedfile-0.0.1.dist-info/top_level.txt
speedfile-0.0.1.dist-info/RECORD
