Metadata-Version: 2.1
Name: speedfile
Version: 0.0.1
Summary: This is the simplest module for quick work with files.
Home-page: https://github.com/y-a-r-i-k/SpeedFile-for-Python
Author: yarik_g
Author-email: gusevyaroslaveggg666@gmail.com
Project-URL: GitHub, https://github.com/y-a-r-i-k/SpeedFile-for-Python
Keywords: files speedfiles
Classifier: Programming Language :: Python :: 3.11
Classifier: License :: OSI Approved :: MIT License
Classifier: Operating System :: OS Independent
Requires-Python: >=3.6
License-File: LICENSE
Requires-Dist: requests (>=2.25.1)
